wspd.cp37-win_amd64.pyd
wspdd-0.0.8.dist-info/LICENSE
wspdd-0.0.8.dist-info/METADATA
wspdd-0.0.8.dist-info/WHEEL
wspdd-0.0.8.dist-info/top_level.txt
wspdd-0.0.8.dist-info/RECORD
