Metadata-Version: 2.1
Name: wspdd
Version: 0.0.8
Summary: A fast WSPD implementation.
Home-page: https://github.com/dmatijev/wspd
Author: Domagoj Matijevic
Author-email: dmaijev@mathos.hr
Requires-Python: >=3.7
License-File: LICENSE
Provides-Extra: test
Requires-Dist: pytest ; extra == 'test'
